pythaiwordcut/__init__.py
pythaiwordcut/core.py
pythaiwordcut/dict/lexitron.txt
pythaiwordcut/dict/negation.txt
pythaiwordcut/dict/stockword.txt
pythaiwordcut-0.1.15-py3.6.egg-info/PKG-INFO
pythaiwordcut-0.1.15-py3.6.egg-info/SOURCES.txt
pythaiwordcut-0.1.15-py3.6.egg-info/dependency_links.txt
pythaiwordcut-0.1.15-py3.6.egg-info/not-zip-safe
pythaiwordcut-0.1.15-py3.6.egg-info/requires.txt
pythaiwordcut-0.1.15-py3.6.egg-info/top_level.txt
pythaiwordcut-0.1.15.dist-info/LICENSE
pythaiwordcut-0.1.15.dist-info/METADATA
pythaiwordcut-0.1.15.dist-info/WHEEL
pythaiwordcut-0.1.15.dist-info/top_level.txt
pythaiwordcut-0.1.15.dist-info/RECORD
