Metadata-Version: 2.1
Name: pythaiwordcut
Version: 0.1.15
Summary: Simple Thai Wordcut in Python using Maximum Matching
Home-page: https://github.com/zenyai/pythaiwordcut
Author: Narongdej Sarnsuwan
Author-email: narongdej@sarnsuwan.com
License: MIT
Platform: UNKNOWN
Requires-Dist: marisa-trie
